expdf2txt/__init__.py
expdf2txt/base.py
expdf2txt/invoice2data.py
expdf2txt/pdf2data.py
expdf2txt-1.1.1.dist-info/METADATA
expdf2txt-1.1.1.dist-info/WHEEL
expdf2txt-1.1.1.dist-info/top_level.txt
expdf2txt-1.1.1.dist-info/RECORD
