Metadata-Version: 2.1
Name: expdf2txt
Version: 1.1.1
Summary: PDF to TXT
Home-page: UNKNOWN
Author: Gaurav Mehra
Author-email: gauravmehra930@gmail.com
License: UNKNOWN
Project-URL: Source, https://github.com/AgTech930/expdftotxt
Keywords: pdf2txt,pdftotxt,invoice2text,invoice2txt,ag tech,gaurav mehra,expdf2txt,pdftoimage,pdf2image
Platform: UNKNOWN
Classifier: Development Status :: 3 - Alpha
Classifier: Intended Audience :: Developers
Classifier: Programming Language :: Python
Requires-Dist: PyMuPDF
Requires-Dist: PyPDF2
Requires-Dist: openai
Requires-Dist: pytesseract
